focus_validator/__init__.py
focus_validator/config_objects/__init__.py
focus_validator/config_objects/common.py
focus_validator/config_objects/focus_to_pandera_schema_converter.py
focus_validator/config_objects/override.py
focus_validator/config_objects/rule.py
focus_validator/data_loaders/__init__.py
focus_validator/data_loaders/csv_data_loader.py
focus_validator/data_loaders/data_loader.py
focus_validator/data_loaders/parquet_data_loader.py
focus_validator/exceptions.py
focus_validator/main.py
focus_validator/outputter/__init__.py
focus_validator/outputter/outputter.py
focus_validator/outputter/outputter_console.py
focus_validator/outputter/outputter_unittest.py
focus_validator/rules/.gitignore
focus_validator/rules/__init__.py
focus_validator/rules/base_rule_definitions/AmortizedCost_IsDecimal.yaml
focus_validator/rules/base_rule_definitions/AmortizedCost_NotNull.yaml
focus_validator/rules/base_rule_definitions/AmortizedCost_Required.yaml
focus_validator/rules/base_rule_definitions/AvailabilityZone_IsString.yaml
focus_validator/rules/base_rule_definitions/AvailabilityZone_Nullable.yaml
focus_validator/rules/base_rule_definitions/BilledCost_IsDecimal.yaml
focus_validator/rules/base_rule_definitions/BilledCost_NotNull.yaml
focus_validator/rules/base_rule_definitions/BilledCost_Required.yaml
focus_validator/rules/base_rule_definitions/BilledCurrency_IsCurrencyCode.yaml
focus_validator/rules/base_rule_definitions/BilledCurrency_NotNull.yaml
focus_validator/rules/base_rule_definitions/BilledCurrency_Required.yaml
focus_validator/rules/base_rule_definitions/BillingAccountId_IsString.yaml
focus_validator/rules/base_rule_definitions/BillingAccountId_NotNull.yaml
focus_validator/rules/base_rule_definitions/BillingAccountId_Required.yaml
focus_validator/rules/base_rule_definitions/BillingAccountName_IsString.yaml
focus_validator/rules/base_rule_definitions/BillingAccountName_Nullable.yaml
focus_validator/rules/base_rule_definitions/BillingAccountName_Required.yaml
focus_validator-0.5.2.dev3.dist-info/LICENSE
focus_validator-0.5.2.dev3.dist-info/METADATA
focus_validator-0.5.2.dev3.dist-info/WHEEL
focus_validator-0.5.2.dev3.dist-info/entry_points.txt
focus_validator-0.5.2.dev3.dist-info/RECORD
