Metadata-Version: 2.1
Name: focus_validator
Version: 0.5.2.dev3
Summary: FOCUS spec validator.
Requires-Python: >=3.8.3,<4.0.0
Classifier: Programming Language :: Python :: 3
Classifier: Programming Language :: Python :: 3.9
Classifier: Programming Language :: Python :: 3.10
Classifier: Programming Language :: Python :: 3.11
Classifier: Programming Language :: Python :: 3.12
Requires-Dist: numpy (>=1.24,<1.25) ; python_version >= "3.8" and python_version < "3.9"
Requires-Dist: numpy (>=1.26,<1.27) ; python_version >= "3.12" and python_version < "3.13"
Requires-Dist: pandas (>=2,<3)
Requires-Dist: pandasql (>=0.7.3,<0.8.0)
Requires-Dist: pandera (>=0.17.2,<0.18.0)
Requires-Dist: pyarrow
Requires-Dist: pydantic (>=2,<3)
Requires-Dist: pytz (>=2023.3.post1,<2024.0)
Requires-Dist: pyyaml
Requires-Dist: requests
Requires-Dist: sqlglot (>=18.7.0,<19.0.0)
Requires-Dist: tabulate
